my_pack/__init__.py
my_pack/my_func.py
Dhrupad123_pack-0.0.1.dist-info/METADATA
Dhrupad123_pack-0.0.1.dist-info/WHEEL
Dhrupad123_pack-0.0.1.dist-info/top_level.txt
Dhrupad123_pack-0.0.1.dist-info/RECORD
