Metadata-Version: 2.1
Name: Dhrupad123-pack
Version: 0.0.1
Summary: marvel characters package
Author: Dhrupad
Author-email: dhrupadjoshi2000@gmail.com
